ecl_package_test-0.8.data/scripts/package.cmd
src/__init__.py
src/builder.py
src/cli.py
src/copy_helper.py
src/dashboard.py
src/make_template.py
src/replace_helper.py
ecl_package_test-0.8.dist-info/METADATA
ecl_package_test-0.8.dist-info/WHEEL
ecl_package_test-0.8.dist-info/entry_points.txt
ecl_package_test-0.8.dist-info/top_level.txt
ecl_package_test-0.8.dist-info/RECORD
