Metadata-Version: 2.1
Name: ecl-package-test
Version: 0.8
Summary: ecl package TBA
Home-page: https://github.com/EarthCodingLab/ecl-package
Author: Earth Coding Lab
Author-email: syw5141@gmail.com
License: MIT
Classifier: Programming Language :: Python :: 3
Classifier: License :: OSI Approved :: MIT License
Classifier: Operating System :: OS Independent
